confluent_avro/__init__.py
confluent_avro/avrolib.py
confluent_avro/exceptions.py
confluent_avro/serde.py
confluent_avro/schema_registry/__init__.py
confluent_avro/schema_registry/auth.py
confluent_avro/schema_registry/client_http.py
confluent_avro/schema_registry/errors.py
confluent_avro-1.8.0.dist-info/LICENSE
confluent_avro-1.8.0.dist-info/WHEEL
confluent_avro-1.8.0.dist-info/METADATA
confluent_avro-1.8.0.dist-info/RECORD
