Metadata-Version: 2.1
Name: confluent_avro
Version: 1.8.0
Summary: An Avro SerDe implementation that integrates with the confluent
Home-page: https://github.com/DhiaTN/confluent-avro-py
License: UNKNOWN
Keywords: avro,kafka,confluent,schema registry
Author: Dhia Abbassi
Author-email: dhia.absi@gmail.com
Requires-Python: >=3.6
Classifier: License :: OSI Approved :: Apache Software License
Classifier: Development Status :: 4 - Beta
Classifier: Programming Language :: Python :: 3 :: Only
Classifier: Programming Language :: Python :: 3.6
Classifier: Programming Language :: Python :: 3.7
Classifier: Programming Language :: Python :: 3.8
Classifier: Operating System :: OS Independent
Classifier: Intended Audience :: Developers
Classifier: Natural Language :: English
Classifier: Topic :: Software Development :: Libraries :: Python Modules
Classifier: Topic :: Software Development :: Libraries
Classifier: Topic :: Software Development
Classifier: Typing :: Typed
Requires-Dist: requests[security] >=2.22.0
Requires-Dist: fastavro >=0.22.9
Requires-Dist: python-status >=1.0.1
Requires-Dist: bumpversion ; extra == "dev"
Requires-Dist: black ==19.10b0 ; extra == "dev"
Requires-Dist: isort ; extra == "dev"
Requires-Dist: mypy ; extra == "dev"
Requires-Dist: pytest >=5.3.5 ; extra == "test"
Requires-Dist: pytest-cov ; extra == "test"
Requires-Dist: pytest-sugar ; extra == "test"
Requires-Dist: pytest-xdist ; extra == "test"
Requires-Dist: responses ; extra == "test"
Provides-Extra: dev
Provides-Extra: test
